django_path_tracer.py
django_path_tracer-1.0.0.dist-info/licenses/LICENSE
django_path_tracer-1.0.0.dist-info/METADATA
django_path_tracer-1.0.0.dist-info/WHEEL
django_path_tracer-1.0.0.dist-info/entry_points.txt
django_path_tracer-1.0.0.dist-info/top_level.txt
django_path_tracer-1.0.0.dist-info/RECORD
